uztvuz/__init__.py
uztvuz/brute.py
uztvuz-0.0.13.dist-info/LICENSE
uztvuz-0.0.13.dist-info/METADATA
uztvuz-0.0.13.dist-info/WHEEL
uztvuz-0.0.13.dist-info/entry_points.txt
uztvuz-0.0.13.dist-info/top_level.txt
uztvuz-0.0.13.dist-info/RECORD
