Metadata-Version: 2.1
Name: uztvuz
Version: 0.0.13
Summary: salom
Author: Sarvar Raxmonov
Author-email: <tturkbola@gmail.com>
License: UNKNOWN
Keywords: uztvuz
Platform: UNKNOWN
Classifier: Development Status :: 1 - Planning
Classifier: Intended Audience :: Developers
Classifier: Programming Language :: Python :: 3
Classifier: Operating System :: Unix
Classifier: Operating System :: MacOS :: MacOS X
Classifier: Operating System :: Microsoft :: Windows
License-File: LICENSE
